AUTHORS.rst
CONTRIBUTING.rst
HISTORY.rst
MANIFEST.in
README.rst
setup.cfg
setup.py
docs/Makefile
docs/authors.rst
docs/conf.py
docs/contributing.rst
docs/history.rst
docs/index.rst
docs/installation.rst
docs/make.bat
docs/readme.rst
docs/usage.rst
goodput/__init__.py
goodput/goodput.py
goodput.egg-info/PKG-INFO
goodput.egg-info/SOURCES.txt
goodput.egg-info/dependency_links.txt
goodput.egg-info/not-zip-safe
goodput.egg-info/top_level.txt
tests/__init__.py
tests/test_goodput.py