Metadata-Version: 1.2
Name: goodput
Version: 0.1.0
Summary: Throughput and performance modeling. 
Home-page: https://github.com/umerazad/goodput
Author: Umer Azad
Author-email: muazad@microsoft.com
License: UNKNOWN
Keywords: goodput
Platform: UNKNOWN
Classifier: Development Status :: 2 - Pre-Alpha
Classifier: Intended Audience :: Developers
Classifier: Natural Language :: English
Classifier: Programming Language :: Python :: 3
Classifier: Programming Language :: Python :: 3.5
Classifier: Programming Language :: Python :: 3.6
Classifier: Programming Language :: Python :: 3.7
Classifier: Programming Language :: Python :: 3.8
Requires-Python: >=3.5
